document_ai_toolkit/__init__.py
document_ai_toolkit/processor.py
document_ai_toolkit/types.py
document_ai_toolkit-0.1.0.dist-info/METADATA
document_ai_toolkit-0.1.0.dist-info/WHEEL
document_ai_toolkit-0.1.0.dist-info/licenses/LICENSE
document_ai_toolkit-0.1.0.dist-info/RECORD
