Metadata-Version: 2.4
Name: document-ai-toolkit
Version: 0.1.0
Summary: Comprehensive document processing toolkit for AI/ML applications
Project-URL: Homepage, https://github.com/pranaym/document-ai-toolkit
Project-URL: Documentation, https://github.com/pranaym/document-ai-toolkit#readme
Project-URL: Repository, https://github.com/pranaym/document-ai-toolkit
Project-URL: Issues, https://github.com/pranaym/document-ai-toolkit/issues
Author: Pranay M
License-Expression: MIT
License-File: LICENSE
Keywords: ai,document-ai,document-processing,machine-learning,nlp,ocr,pdf-extraction,table-extraction,text-extraction
Classifier: Development Status :: 4 - Beta
Classifier: Intended Audience :: Developers
Classifier: Intended Audience :: Science/Research
Classifier: License :: OSI Approved :: MIT License
Classifier: Operating System :: OS Independent
Classifier: Programming Language :: Python :: 3
Classifier: Programming Language :: Python :: 3.8
Classifier: Programming Language :: Python :: 3.9
Classifier: Programming Language :: Python :: 3.10
Classifier: Programming Language :: Python :: 3.11
Classifier: Programming Language :: Python :: 3.12
Classifier: Topic :: Scientific/Engineering :: Artificial Intelligence
Classifier: Topic :: Software Development :: Libraries :: Python Modules
Classifier: Topic :: Text Processing :: General
Requires-Python: >=3.8
Provides-Extra: all
Requires-Dist: pdfplumber>=0.10.0; extra == 'all'
Requires-Dist: pillow>=10.0.0; extra == 'all'
Requires-Dist: pymupdf>=1.23.0; extra == 'all'
Requires-Dist: pytesseract>=0.3.10; extra == 'all'
Requires-Dist: python-docx>=1.0.0; extra == 'all'
Requires-Dist: torch>=2.0.0; extra == 'all'
Requires-Dist: transformers>=4.30.0; extra == 'all'
Provides-Extra: dev
Requires-Dist: black>=23.0.0; extra == 'dev'
Requires-Dist: mypy>=1.0.0; extra == 'dev'
Requires-Dist: pytest-cov>=4.0.0; extra == 'dev'
Requires-Dist: pytest>=7.0.0; extra == 'dev'
Requires-Dist: ruff>=0.1.0; extra == 'dev'
Provides-Extra: docx
Requires-Dist: python-docx>=1.0.0; extra == 'docx'
Provides-Extra: ml
Requires-Dist: torch>=2.0.0; extra == 'ml'
Requires-Dist: transformers>=4.30.0; extra == 'ml'
Provides-Extra: ocr
Requires-Dist: pillow>=10.0.0; extra == 'ocr'
Requires-Dist: pytesseract>=0.3.10; extra == 'ocr'
Provides-Extra: pdf
Requires-Dist: pdfplumber>=0.10.0; extra == 'pdf'
Requires-Dist: pymupdf>=1.23.0; extra == 'pdf'
